histogrammar/__init__.py
histogrammar/convenience.py
histogrammar/defs.py
histogrammar/resources.py
histogrammar/sparksql.py
histogrammar/specialized.py
histogrammar/util.py
histogrammar/version.py
histogrammar/dfinterface/__init__.py
histogrammar/dfinterface/addmethods.py
histogrammar/dfinterface/filling_utils.py
histogrammar/dfinterface/histogram_filler_base.py
histogrammar/dfinterface/make_histograms.py
histogrammar/dfinterface/pandas_histogrammar.py
histogrammar/dfinterface/spark_histogrammar.py
histogrammar/notebooks/__init__.py
histogrammar/notebooks/histogrammar_tutorial_advanced.ipynb
histogrammar/notebooks/histogrammar_tutorial_basic.ipynb
histogrammar/notebooks/histogrammar_tutorial_exercises.ipynb
histogrammar/plot/__init__.py
histogrammar/plot/bokeh.py
histogrammar/plot/hist_numpy.py
histogrammar/plot/matplotlib.py
histogrammar/primitives/__init__.py
histogrammar/primitives/average.py
histogrammar/primitives/bag.py
histogrammar/primitives/bin.py
histogrammar/primitives/categorize.py
histogrammar/primitives/centrallybin.py
histogrammar/primitives/collection.py
histogrammar/primitives/count.py
histogrammar/primitives/deviate.py
histogrammar/primitives/fraction.py
histogrammar/primitives/irregularlybin.py
histogrammar/primitives/minmax.py
histogrammar/primitives/select.py
histogrammar/primitives/sparselybin.py
histogrammar/primitives/stack.py
histogrammar/primitives/sum.py
histogrammar/test_data/__init__.py
histogrammar/test_data/test.csv.gz
histogrammar-1.1.2.dist-info/licenses/LICENSE
histogrammar-1.1.2.dist-info/licenses/NOTICE
histogrammar-1.1.2.dist-info/METADATA
histogrammar-1.1.2.dist-info/WHEEL
histogrammar-1.1.2.dist-info/top_level.txt
histogrammar-1.1.2.dist-info/RECORD
