Metadata-Version: 2.4
Name: histogrammar
Version: 1.1.2
Summary: Histograms for Pandas/Spark/Numpy
Author-email: Max Baak <maxbaak@gmail.com>, "Jim Pivarski (DIANA-HEP)" <pivarski@fnal.gov>
Maintainer-email: Max Baak <maxbaak@gmail.com>
License:                                  Apache License
Project-URL: repository, https://github.com/histogrammar/histogrammar-python
Keywords: pandas,spark,data-science,data-analysis,statistics,python,jupyter,ipython
Classifier: Development Status :: 5 - Production/Stable
Classifier: Environment :: Console
Classifier: Intended Audience :: Science/Research
Classifier: License :: OSI Approved :: Apache Software License
Classifier: Topic :: Scientific/Engineering :: Information Analysis
Classifier: Topic :: Scientific/Engineering :: Mathematics
Classifier: Topic :: Scientific/Engineering :: Physics
Requires-Python: >=3.9
License-File: LICENSE
License-File: NOTICE
Requires-Dist: numpy
Requires-Dist: tqdm
Requires-Dist: joblib>=0.14.0
Provides-Extra: pandas
Requires-Dist: pandas; extra == "pandas"
Provides-Extra: spark
Requires-Dist: pyspark; extra == "spark"
Provides-Extra: test
Requires-Dist: ipykernel>=5.1.3; extra == "test"
Requires-Dist: jupyter_client>=5.2.3; extra == "test"
Requires-Dist: matplotlib; extra == "test"
Requires-Dist: pandas; extra == "test"
Requires-Dist: pre-commit>=2.9.0; extra == "test"
Requires-Dist: pytest-notebook>=0.6.1; extra == "test"
Requires-Dist: pytest>=4.0.2; extra == "test"
Provides-Extra: test-numpy-pre2
Requires-Dist: numpy<2; extra == "test-numpy-pre2"
Requires-Dist: pandas<2; extra == "test-numpy-pre2"
Provides-Extra: test-spark-pre2
Requires-Dist: pyspark<4; python_version <= "3.11" and extra == "test-spark-pre2"
Dynamic: license-file
